EasyDataSharing/__init__.py
EasyDataSharing-1.3.5.dist-info/METADATA
EasyDataSharing-1.3.5.dist-info/WHEEL
EasyDataSharing-1.3.5.dist-info/top_level.txt
EasyDataSharing-1.3.5.dist-info/RECORD
