Metadata-Version: 2.1
Name: EasyDataSharing
Version: 1.3.5
Summary: For Sharing Data between files
Home-page: https://github.com/FriesCoin/EasyDataSharing
Author: Damian Payano
Author-email: damiangamesss464@gmail.com
Classifier: Programming Language :: Python :: 3
Classifier: License :: OSI Approved :: MIT License
Classifier: Operating System :: OS Independent
Requires-Python: >=3.7
